yta_image_advanced_ai/__init__.py
yta_image_advanced_ai/descriptor.py
yta_image_advanced_ai/generator.py
yta_image_advanced_ai-0.0.5.dist-info/LICENSE
yta_image_advanced_ai-0.0.5.dist-info/METADATA
yta_image_advanced_ai-0.0.5.dist-info/WHEEL
yta_image_advanced_ai-0.0.5.dist-info/RECORD
